[
  {
    "nombre": "Play",
    "key": "KEY_1",
    "accion": "teclas",
    "opciones": {
      "teclas": ["space"]
    }
  },
  {
    "nombre": "TrimAll",
    "key": "KEY_5",
    "accion": "teclas",
    "opciones": {
      "teclas": ["shift", "t"]
    }
  },
  {
    "nombre": "Guardar",
    "key": "KEY_3",
    "accion": "teclas",
    "opciones": {
      "teclas": ["ctrl", "s"]
    }
  },
  {
    "nombre": "Concatenar",
    "key": "KEY_4",
    "accion": "teclas",
    "opciones": {
      "teclas": ["shift", "c"]
    }
  },
  {
    "nombre": "Borrar",
    "key": "KEY_2",
    "accion": "teclas",
    "opciones": {
      "teclas": ["x"]
    }
  },
  {
    "nombre": "Mover",
    "key": "KEY_6",
    "accion": "teclas",
    "opciones": {
      "teclas": ["g"]
    }
  },
  {
    "nombre": "Mute",
    "key": "KEY_7",
    "accion": "teclas",
    "opciones": {
      "teclas": ["h"]
    }
  }
]
